{
  "id": "incremental-breakdown-repo-memory",
  "name": "incremental-breakdown-repo-memory",
  "title": "增量式 task 拆解:第二次拆解參考既有任務 + repo 記憶隔離",
  "description": "",
  "status": "completed",
  "dev_type": null,
  "scope": null,
  "package": null,
  "priority": "P2",
  "creator": "opal",
  "assignee": "opal",
  "createdAt": "2026-06-15",
  "completedAt": "2026-06-15",
  "branch": "feature/incremental-breakdown",
  "base_branch": "develop",
  "worktree_path": null,
  "commit": null,
  "pr_url": null,
  "subtasks": [],
  "children": [],
  "parent": null,
  "relatedFiles": [],
  "notes": "",
  "meta": {}
}